premium_lib.py
premiumcalculator_mylibrary-1.0.8.dist-info/METADATA
premiumcalculator_mylibrary-1.0.8.dist-info/WHEEL
premiumcalculator_mylibrary-1.0.8.dist-info/top_level.txt
premiumcalculator_mylibrary-1.0.8.dist-info/RECORD
