Metadata-Version: 2.4
Name: premiumcalculator_mylibrary
Version: 1.0.8
Summary: Phone insurance premium calculation library
Author-email: Shubham Hazare <gokuireland2820@gmail.com>
License: MIT
Project-URL: Homepage, https://github.com/shubhamhazare/premiumcalculator
Requires-Python: >=3.7
